doc_intel/__init__.py
doc_intel/despace.py
doc_intel/manage_diction.py
doc_intel/text_laundry.py
doc_intel/words.txt
doc_intel-1.0.1.dist-info/LICENSE
doc_intel-1.0.1.dist-info/METADATA
doc_intel-1.0.1.dist-info/WHEEL
doc_intel-1.0.1.dist-info/entry_points.txt
doc_intel-1.0.1.dist-info/top_level.txt
doc_intel-1.0.1.dist-info/RECORD
