Metadata-Version: 2.1
Name: doc-intel
Version: 1.0.1
Summary: Your solution to cleansing PDF documents for preprocessing for NLP
Home-page: https://github.com/VishakArudhra/doc_intel
Author: Vishak Arudhra
Author-email: vishakarudhra@gmail.com
License: MIT
Platform: UNKNOWN
Classifier: License :: OSI Approved :: MIT License
Classifier: Programming Language :: Python :: 3.0
Classifier: Programming Language :: Python :: 3.8
Requires-Dist: pandas
Requires-Dist: Unidecode
Requires-Dist: unicodedata2
Requires-Dist: clean-text
Requires-Dist: Levenshtein
Requires-Dist: PyMuPDF
Requires-Dist: regex
